panoptica/__init__.py
panoptica/_functionals.py
panoptica/cli.py
panoptica/configs/SegmentationClassGroups_example_unmatchedinstancepair.yaml
panoptica/configs/panoptica_evaluator_BRATS.yaml
panoptica/configs/panoptica_evaluator_ISLES.yaml
panoptica/configs/panoptica_evaluator_VERSE.yaml
panoptica/configs/panoptica_evaluator_default.yaml
panoptica/configs/panoptica_evaluator_unmatched_instance.yaml
panoptica/instance_approximator.py
panoptica/instance_evaluator.py
panoptica/instance_matcher.py
panoptica/metrics/__init__.py
panoptica/metrics/assd.py
panoptica/metrics/center_distance.py
panoptica/metrics/cldice.py
panoptica/metrics/dice.py
panoptica/metrics/hausdorff_distance.py
panoptica/metrics/iou.py
panoptica/metrics/metrics.py
panoptica/metrics/normalized_surface_dice.py
panoptica/metrics/relative_absolute_volume_error.py
panoptica/metrics/relative_volume_difference.py
panoptica/panoptica_aggregator.py
panoptica/panoptica_evaluator.py
panoptica/panoptica_result.py
panoptica/panoptica_statistics.py
panoptica/utils/__init__.py
panoptica/utils/citation_reminder.py
panoptica/utils/config.py
panoptica/utils/constants.py
panoptica/utils/edge_case_handling.py
panoptica/utils/filepath.py
panoptica/utils/input_check_and_conversion/check_nibabel_image.py
panoptica/utils/input_check_and_conversion/check_nrrd_image.py
panoptica/utils/input_check_and_conversion/check_numpy_array.py
panoptica/utils/input_check_and_conversion/check_sitk_image.py
panoptica/utils/input_check_and_conversion/check_torch_image.py
panoptica/utils/input_check_and_conversion/input_data_type_checker.py
panoptica/utils/input_check_and_conversion/sanity_checker.py
panoptica/utils/instancelabelmap.py
panoptica/utils/label_group.py
panoptica/utils/numpy_utils.py
panoptica/utils/parallel_processing.py
panoptica/utils/processing_pair.py
panoptica/utils/segmentation_class.py
panoptica/utils/timing.py
panoptica-1.5.0.dist-info/LICENSE
panoptica-1.5.0.dist-info/METADATA
panoptica-1.5.0.dist-info/WHEEL
panoptica-1.5.0.dist-info/entry_points.txt
panoptica-1.5.0.dist-info/RECORD
