Metadata-Version: 2.3
Name: panoptica
Version: 1.5.0
Summary: Panoptic Quality (PQ) computation for binary masks.
Author: Hendrik Möller
Author-email: hendrik.moeller@tum.de
Requires-Python: >=3.10,<4.0
Classifier: Programming Language :: Python :: 3
Classifier: Programming Language :: Python :: 3.10
Classifier: Programming Language :: Python :: 3.11
Classifier: Programming Language :: Python :: 3.12
Classifier: Programming Language :: Python :: 3.13
Requires-Dist: connected-components-3d (>=3.12.3,<4.0.0)
Requires-Dist: numpy (>=1.20.0,<2.0.0)
Requires-Dist: pandas (>=2.1.0,<3.0.0)
Requires-Dist: plotly (>=5.16.1,<6.0.0)
Requires-Dist: rich (>=13.6.0,<14.0.0)
Requires-Dist: ruamel.yaml (>=0.18.6,<1.0.0)
Requires-Dist: scikit-image (>=0.22.0,<1.0.0)
Requires-Dist: scipy (>=1.7.0,<2.0.0)
Requires-Dist: typer (>=0.15.0,<1.0.0)
Project-URL: Documentation, https://panoptica.readthedocs.io/
Project-URL: Homepage, https://github.com/BrainLesion/panoptica
Project-URL: Repository, https://github.com/BrainLesion/panoptica
